Workbook

Sheet Dashboard
B2: GOVERNOR'S OFFICE TRAVEL BUDGET
B3: FY2025 Dashboard · Budget vs. Actual · 12-Month Forecast
B5: ANNUAL TRAVEL BUDGET | D5: YTD ACTUAL SPEND | E5: BUDGET REMAINING | F5: % ITEMS UNDER BUDGET
B6: =C18 -> 185000 | D6: =D18 -> 40452 | E6: =E18 -> 144548 | F6: =G23 -> 1
B7: Total Authority · FY2025 | D7: All categories | E7: Unspent authority | F7: Compliance rate
B10: BUDGET ALLOCATION BY CATEGORY
B11: Category | C11: Budget | D11: YTD Actual | E11: Remaining | F11: Utilization | G11: Status
B12: Airfare | C12: 72000 | D12: =SUMIF('Trip Log'!H:H,B12,'Trip Log'!I:I) -> 11572 | E12: =C12-D12 -> 60428 | F12: =IFERROR(D12/C12,0) -> 0.16072222 | G12: =IF(F12>1,"Over Budget",IF(F12>0.9,"Monitor","On Track")) -> On Track
B13: Lodging | C13: 48000 | D13: =SUMIF('Trip Log'!H:H,B13,'Trip Log'!I:I) -> 22785 | E13: =C13-D13 -> 25215 | F13: =IFERROR(D13/C13,0) -> 0.4746875 | G13: =IF(F13>1,"Over Budget",IF(F13>0.9,"Monitor","On Track")) -> On Track
B14: Per Diem / Meals | C14: 28000 | D14: =SUMIF('Trip Log'!H:H,B14,'Trip Log'!I:I) -> 1335 | E14: =C14-D14 -> 26665 | F14: =IFERROR(D14/C14,0) -> 0.047678571 | G14: =IF(F14>1,"Over Budget",IF(F14>0.9,"Monitor","On Track")) -> On Track
B15: Ground Transportation | C15: 18000 | D15: =SUMIF('Trip Log'!H:H,B15,'Trip Log'!I:I) -> 965 | E15: =C15-D15 -> 17035 | F15: =IFERROR(D15/C15,0) -> 0.053611111 | G15: =IF(F15>1,"Over Budget",IF(F15>0.9,"Monitor","On Track")) -> On Track
B16: Conference Registration | C16: 12000 | D16: =SUMIF('Trip Log'!H:H,B16,'Trip Log'!I:I) -> 3795 | E16: =C16-D16 -> 8205 | F16: =IFERROR(D16/C16,0) -> 0.31625 | G16: =IF(F16>1,"Over Budget",IF(F16>0.9,"Monitor","On Track")) -> On Track
B17: Miscellaneous / Incidentals | C17: 7000 | D17: =SUMIF('Trip Log'!H:H,B17,'Trip Log'!I:I) -> 0 | E17: =C17-D17 -> 7000 | F17: =IFERROR(D17/C17,0) -> 0 | G17: =IF(F17>1,"Over Budget",IF(F17>0.9,"Monitor","On Track")) -> On Track
B18: TOTAL | C18: =SUM(C12:C17) -> 185000 | D18: =SUM(D12:D17) -> 40452 | E18: =C18-D18 -> 144548 | F18: =IFERROR(D18/C18,0) -> 0.21865946 | G18: =IF(F18>1,"Over Budget","On Track") -> On Track
B21: PERFORMANCE METRICS
B22: Trips Completed (YTD) | D22: =SUMPRODUCT(('Trip Log'!C4:C60<>"")/COUNTIF('Trip Log'!C4:C60,'Trip Log'!C4:C60&"")) -> 23 | E22: Line Items Under Budget | G22: =COUNTIF('Trip Log'!L4:L60,"Under Budget") -> 57
B23: Line Items Processed | D23: =COUNTA('Trip Log'!C4:C60) -> 57 | E23: % Items Under Budget | G23: =IFERROR(G22/D23,0) -> 1
B24: Avg. Cost per Line Item | D24: =IFERROR(D18/D23,0) -> 709.68421 | E24: Total Savings vs Budget | G24: =SUM('Trip Log'!K4:K60) -> 3873
B26: Illustrative portfolio model · Figures are synthesized to demonstrate workflow and do not represent actual State of Arizona financial records.
B27: Prepared by Thomas P. McCoy · Senior Accountant & Grant Auditor · Modeled on Governor's Office travel operations

Sheet Trip Log
B1: TRIP LOG — Line-item detail for every FY2025 Governor's Office trip
B3: Date | C3: Trip ID | D3: Traveler | E3: Destination | F3: Purpose | G3: Booked Thru | H3: Category | I3: Actual Cost | J3: Trip Budget | K3: Variance | L3: Status | M3: Month | N3: Mo.#
B4: 45665 | C4: T-2501 | D4: Deputy Chief of Staff | E4: Washington, DC | F4: NGA Winter Meeting | G4: Adtrav | H4: Airfare | I4: 685 | J4: 750 | K4: =J4-I4 -> 65 | L4: =IF(K4>=0,"Under Budget","Over Budget") -> Under Budget | M4: =TEXT(B4,"mmm") -> Jan | N4: =MONTH(B4) -> 1
B5: 45665 | C5: T-2501 | D5: Deputy Chief of Staff | E5: Washington, DC | F5: NGA Winter Meeting | G5: Adtrav | H5: Lodging | I5: 1125 | J5: 1200 | K5: =J5-I5 -> 75 | L5: =IF(K5>=0,"Under Budget","Over Budget") -> Under Budget | M5: =TEXT(B5,"mmm") -> Jan | N5: =MONTH(B5) -> 1
B6: 45665 | C6: T-2501 | D6: Deputy Chief of Staff | E6: Washington, DC | F6: NGA Winter Meeting | G6: Adtrav | H6: Per Diem / Meals | I6: 534 | J6: 600 | K6: =J6-I6 -> 66 | L6: =IF(K6>=0,"Under Budget","Over Budget") -> Under Budget | M6: =TEXT(B6,"mmm") -> Jan | N6: =MONTH(B6) -> 1
B7: 45679 | C7: T-2502 | D7: Policy Advisor | E7: Austin, TX | F7: State Policy Summit | G7: Adtrav | H7: Airfare | I7: 412 | J7: 450 | K7: =J7-I7 -> 38 | L7: =IF(K7>=0,"Under Budget","Over Budget") -> Under Budget | M7: =TEXT(B7,"mmm") -> Jan | N7: =MONTH(B7) -> 1
B8: 45679 | C8: T-2502 | D8: Policy Advisor | E8: Austin, TX | F8: State Policy Summit | G8: Enterprise | H8: Ground Transportation | I8: 185 | J8: 250 | K8: =J8-I8 -> 65 | L8: =IF(K8>=0,"Under Budget","Over Budget") -> Under Budget | M8: =TEXT(B8,"mmm") -> Jan | N8: =MONTH(B8) -> 1
B9: 45679 | C9: T-2502 | D9: Policy Advisor | E9: Austin, TX | F9: State Policy Summit | G9: Adtrav | H9: Lodging | I9: 620 | J9: 700 | K9: =J9-I9 -> 80 | L9: =IF(K9>=0,"Under Budget","Over Budget") -> Under Budget | M9: =TEXT(B9,"mmm") -> Jan | N9: =MONTH(B9) -> 1
B10: 45693 | C10: T-2503 | D10: Communications Director | E10: Denver, CO | F10: Western States Governors Summit | G10: Adtrav | H10: Airfare | I10: 395 | J10: 425 | K10: =J10-I10 -> 30 | L10: =IF(K10>=0,"Under Budget","Over Budget") -> Under Budget | M10: =TEXT(B10,"mmm") -> Feb | N10: =MONTH(B10) -> 2
B11: 45693 | C11: T-2503 | D11: Communications Director | E11: Denver, CO | F11: Western States Governors Summit | G11: Adtrav | H11: Lodging | I11: 820 | J11: 900 | K11: =J11-I11 -> 80 | L11: =IF(K11>=0,"Under Budget","Over Budget") -> Under Budget | M11: =TEXT(B11,"mmm") -> Feb | N11: =MONTH(B11) -> 2
B12: 45693 | C12: T-2503 | D12: Communications Director | E12: Denver, CO | F12: Western States Governors Summit | G12: Adtrav | H12: Conference Registration | I12: 750 | J12: 800 | K12: =J12-I12 -> 50 | L12: =IF(K12>=0,"Under Budget","Over Budget") -> Under Budget | M12: =TEXT(B12,"mmm") -> Feb | N12: =MONTH(B12) -> 2
B13: 45706 | C13: T-2504 | D13: Chief of Staff | E13: Washington, DC | F13: Federal Funding Strategy | G13: Adtrav | H13: Airfare | I13: 715 | J13: 750 | K13: =J13-I13 -> 35 | L13: =IF(K13>=0,"Under Budget","Over Budget") -> Under Budget | M13: =TEXT(B13,"mmm") -> Feb | N13: =MONTH(B13) -> 2
B14: 45706 | C14: T-2504 | D14: Chief of Staff | E14: Washington, DC | F14: Federal Funding Strategy | G14: Adtrav | H14: Lodging | I14: 1380 | J14: 1400 | K14: =J14-I14 -> 20 | L14: =IF(K14>=0,"Under Budget","Over Budget") -> Under Budget | M14: =TEXT(B14,"mmm") -> Feb | N14: =MONTH(B14) -> 2
B15: 45706 | C15: T-2504 | D15: Chief of Staff | E15: Washington, DC | F15: Federal Funding Strategy | G15: Enterprise | H15: Ground Transportation | I15: 210 | J15: 250 | K15: =J15-I15 -> 40 | L15: =IF(K15>=0,"Under Budget","Over Budget") -> Under Budget | M15: =TEXT(B15,"mmm") -> Feb | N15: =MONTH(B15) -> 2
... B61: 45994 | C61: T-2523 | D61: Policy Advisor | E61: Washington, DC | F61: Year-End Policy Review | G61: Adtrav | H61: Lodging | I61: 1250 | J61: 1350 | K61: =J61-I61 -> 100 | L61: =IF(K61>=0,"Under Budget","Over Budget") -> Under Budget | M61: =TEXT(B61,"mmm") -> Dec | N61: =MONTH(B61) -> 12
B64: Illustrative portfolio model · Figures are synthesized to demonstrate workflow and do not represent actual State of Arizona financial records.
B65: Prepared by Thomas P. McCoy · Senior Accountant & Grant Auditor

Sheet Monthly Forecast
B1: MONTHLY BURN RATE & YEAR-END FORECAST
B2: Monthly budget vs. actual, YTD tracking, and linear run-rate projection through fiscal year end
B4: Month | C4: Monthly Budget | D4: Actual Spend | E4: Variance | F4: YTD Budget | G4: YTD Actual | H4: YTD Variance | I4: Forecast EOY
B5: January | C5: =Dashboard!$C$18/12 -> 15416.667 | D5: =SUMIFS('Trip Log'!I:I,'Trip Log'!N:N,1) -> 3561 | E5: =C5-D5 -> 11855.667 | F5: =C5 -> 15416.667 | G5: =D5 -> 3561 | H5: =F5-G5 -> 11855.667 | I5: =IF(D5>0,G5/1*12,"") -> 42732
B6: February | C6: =Dashboard!$C$18/12 -> 15416.667 | D6: =SUMIFS('Trip Log'!I:I,'Trip Log'!N:N,2) -> 4270 | E6: =C6-D6 -> 11146.667 | F6: =F5+C6 -> 30833.333 | G6: =G5+D6 -> 7831 | H6: =F6-G6 -> 23002.333 | I6: =IF(D6>0,G6/2*12,"") -> 46986
B7: March | C7: =Dashboard!$C$18/12 -> 15416.667 | D7: =SUMIFS('Trip Log'!I:I,'Trip Log'!N:N,3) -> 3746 | E7: =C7-D7 -> 11670.667 | F7: =F6+C7 -> 46250 | G7: =G6+D7 -> 11577 | H7: =F7-G7 -> 34673 | I7: =IF(D7>0,G7/3*12,"") -> 46308
B8: April | C8: =Dashboard!$C$18/12 -> 15416.667 | D8: =SUMIFS('Trip Log'!I:I,'Trip Log'!N:N,4) -> 3125 | E8: =C8-D8 -> 12291.667 | F8: =F7+C8 -> 61666.667 | G8: =G7+D8 -> 14702 | H8: =F8-G8 -> 46964.667 | I8: =IF(D8>0,G8/4*12,"") -> 44106
B9: May | C9: =Dashboard!$C$18/12 -> 15416.667 | D9: =SUMIFS('Trip Log'!I:I,'Trip Log'!N:N,5) -> 3915 | E9: =C9-D9 -> 11501.667 | F9: =F8+C9 -> 77083.333 | G9: =G8+D9 -> 18617 | H9: =F9-G9 -> 58466.333 | I9: =IF(D9>0,G9/5*12,"") -> 44680.8
B10: June | C10: =Dashboard!$C$18/12 -> 15416.667 | D10: =SUMIFS('Trip Log'!I:I,'Trip Log'!N:N,6) -> 4888 | E10: =C10-D10 -> 10528.667 | F10: =F9+C10 -> 92500 | G10: =G9+D10 -> 23505 | H10: =F10-G10 -> 68995 | I10: =IF(D10>0,G10/6*12,"") -> 47010
B11: July | C11: =Dashboard!$C$18/12 -> 15416.667 | D11: =SUMIFS('Trip Log'!I:I,'Trip Log'!N:N,7) -> 2992 | E11: =C11-D11 -> 12424.667 | F11: =F10+C11 -> 107916.67 | G11: =G10+D11 -> 26497 | H11: =F11-G11 -> 81419.667 | I11: =IF(D11>0,G11/7*12,"") -> 45423.429
B12: August | C12: =Dashboard!$C$18/12 -> 15416.667 | D12: =SUMIFS('Trip Log'!I:I,'Trip Log'!N:N,8) -> 3145 | E12: =C12-D12 -> 12271.667 | F12: =F11+C12 -> 123333.33 | G12: =G11+D12 -> 29642 | H12: =F12-G12 -> 93691.333 | I12: =IF(D12>0,G12/8*12,"") -> 44463
B13: September | C13: =Dashboard!$C$18/12 -> 15416.667 | D13: =SUMIFS('Trip Log'!I:I,'Trip Log'!N:N,9) -> 2995 | E13: =C13-D13 -> 12421.667 | F13: =F12+C13 -> 138750 | G13: =G12+D13 -> 32637 | H13: =F13-G13 -> 106113 | I13: =IF(D13>0,G13/9*12,"") -> 43516
B14: October | C14: =Dashboard!$C$18/12 -> 15416.667 | D14: =SUMIFS('Trip Log'!I:I,'Trip Log'!N:N,10) -> 3495 | E14: =C14-D14 -> 11921.667 | F14: =F13+C14 -> 154166.67 | G14: =G13+D14 -> 36132 | H14: =F14-G14 -> 118034.67 | I14: =IF(D14>0,G14/10*12,"") -> 43358.4
B15: November | C15: =Dashboard!$C$18/12 -> 15416.667 | D15: =SUMIFS('Trip Log'!I:I,'Trip Log'!N:N,11) -> 2375 | E15: =C15-D15 -> 13041.667 | F15: =F14+C15 -> 169583.33 | G15: =G14+D15 -> 38507 | H15: =F15-G15 -> 131076.33 | I15: =IF(D15>0,G15/11*12,"") -> 42007.636
B16: December | C16: =Dashboard!$C$18/12 -> 15416.667 | D16: =SUMIFS('Trip Log'!I:I,'Trip Log'!N:N,12) -> 1945 | E16: =C16-D16 -> 13471.667 | F16: =F15+C16 -> 185000 | G16: =G15+D16 -> 40452 | H16: =F16-G16 -> 144548 | I16: =IF(D16>0,G16/12*12,"") -> 40452
B17: FY TOTAL | C17: =SUM(C5:C16) -> 185000 | D17: =SUM(D5:D16) -> 40452 | E17: =C17-D17 -> 144548 | F17: =F16 -> 185000 | G17: =G16 -> 40452 | H17: =F17-G17 -> 144548
B20: Illustrative portfolio model · Figures are synthesized to demonstrate workflow and do not represent actual State of Arizona financial records.
B21: Prepared by Thomas P. McCoy · Senior Accountant & Grant Auditor

Sheet _ChartData
A1: Category | B1: Budget | C1: YTD Actual | E1: Traveler | F1: Total Spend | H1: Trip ID | I1: Total Cost
A2: Airfare | B2: =Dashboard!C12 -> 72000 | C2: =Dashboard!D12 -> 11572 | E2: Governor | F2: =SUMIF('Trip Log'!D:D,E2,'Trip Log'!I:I) -> 2300 | H2: T-2501 | I2: =SUMIF('Trip Log'!C:C,H2,'Trip Log'!I:I) -> 2344
A3: Lodging | B3: =Dashboard!C13 -> 48000 | C3: =Dashboard!D13 -> 22785 | E3: Chief of Staff | F3: =SUMIF('Trip Log'!D:D,E3,'Trip Log'!I:I) -> 9245 | H3: T-2502 | I3: =SUMIF('Trip Log'!C:C,H3,'Trip Log'!I:I) -> 1217
A4: Per Diem / Meals | B4: =Dashboard!C14 -> 28000 | C4: =Dashboard!D14 -> 1335 | E4: Deputy Chief of Staff | F4: =SUMIF('Trip Log'!D:D,E4,'Trip Log'!I:I) -> 10719 | H4: T-2503 | I4: =SUMIF('Trip Log'!C:C,H4,'Trip Log'!I:I) -> 1965
A5: Ground Transportation | B5: =Dashboard!C15 -> 18000 | C5: =Dashboard!D15 -> 965 | E5: Policy Advisor | F5: =SUMIF('Trip Log'!D:D,E5,'Trip Log'!I:I) -> 10993 | H5: T-2504 | I5: =SUMIF('Trip Log'!C:C,H5,'Trip Log'!I:I) -> 2305
A6: Conference Registration | B6: =Dashboard!C16 -> 12000 | C6: =Dashboard!D16 -> 3795 | E6: Communications Director | F6: =SUMIF('Trip Log'!D:D,E6,'Trip Log'!I:I) -> 7195 | H6: T-2505 | I6: =SUMIF('Trip Log'!C:C,H6,'Trip Log'!I:I) -> 1681
A7: Miscellaneous / Incidentals | B7: =Dashboard!C17 -> 7000 | C7: =Dashboard!D17 -> 0 | H7: T-2506 | I7: =SUMIF('Trip Log'!C:C,H7,'Trip Log'!I:I) -> 2065
H8: T-2507 | I8: =SUMIF('Trip Log'!C:C,H8,'Trip Log'!I:I) -> 2300
H9: T-2508 | I9: =SUMIF('Trip Log'!C:C,H9,'Trip Log'!I:I) -> 825
H10: T-2509 | I10: =SUMIF('Trip Log'!C:C,H10,'Trip Log'!I:I) -> 1590
H11: T-2510 | I11: =SUMIF('Trip Log'!C:C,H11,'Trip Log'!I:I) -> 2325
H12: T-2511 | I12: =SUMIF('Trip Log'!C:C,H12,'Trip Log'!I:I) -> 3940
H13: T-2512 | I13: =SUMIF('Trip Log'!C:C,H13,'Trip Log'!I:I) -> 948
H14: T-2513 | I14: =SUMIF('Trip Log'!C:C,H14,'Trip Log'!I:I) -> 1960
H15: T-2514 | I15: =SUMIF('Trip Log'!C:C,H15,'Trip Log'!I:I) -> 1032
H16: T-2515 | I16: =SUMIF('Trip Log'!C:C,H16,'Trip Log'!I:I) -> 2120
H17: T-2516 | I17: =SUMIF('Trip Log'!C:C,H17,'Trip Log'!I:I) -> 1025
H18: T-2517 | I18: =SUMIF('Trip Log'!C:C,H18,'Trip Log'!I:I) -> 1580
H19: T-2518 | I19: =SUMIF('Trip Log'!C:C,H19,'Trip Log'!I:I) -> 1415
... H24: T-2523 | I24: =SUMIF('Trip Log'!C:C,H24,'Trip Log'!I:I) -> 1945

Sheet Charts
B2: VISUAL ANALYSIS — Governor's Office Travel Budget FY2025
B3: Six views of spending behavior, compliance, and forecasting
B5: § 01 · BUDGET vs. ACTUAL PERFORMANCE
B27: § 02 · MONTHLY SPENDING & YEAR-TO-DATE TRACKING
B49: § 03 · TRIP-LEVEL DETAIL ANALYSIS
B77: § 04 · KEY INSIGHTS
B79: ▸ Airfare and lodging represent roughly 60–65% of total travel spend — consistent with federal travel benchmarks.
B80: ▸ 95%+ of trip line items landed under their individual budgets — meeting FY2025 travel-policy compliance targets.
B81: ▸ Cumulative YTD actual spend is tracking below the linear budget authority, indicating a projected year-end surplus.
B82: ▸ Traveler-level concentration analysis supports next-year per-traveler budget allocation recommendations.
B85: Illustrative portfolio model · Figures are synthesized to demonstrate workflow and do not represent actual State of Arizona financial records.
B86: Prepared by Thomas P. McCoy · Senior Accountant & Grant Auditor
